<annotation>
	<folder></folder>
	<filename>levle1_125_jpg.rf.7b4e56625855415be6910725f5b5e971.jpg</filename>
	<path>levle1_125_jpg.rf.7b4e56625855415be6910725f5b5e971.jpg</path>
	<source>
		<database>roboflow.com</database>
	</source>
	<size>
		<width>640</width>
		<height>640</height>
		<depth>3</depth>
	</size>
	<segmented>0</segmented>
	<object>
		<name>pustules</name>
		<pose>Unspecified</pose>
		<truncated>0</truncated>
		<difficult>0</difficult>
		<occluded>0</occluded>
		<bndbox>
			<xmin>267</xmin>
			<xmax>290</xmax>
			<ymin>480</ymin>
			<ymax>498</ymax>
		</bndbox>
	</object>
	<object>
		<name>pustules</name>
		<pose>Unspecified</pose>
		<truncated>0</truncated>
		<difficult>0</difficult>
		<occluded>0</occluded>
		<bndbox>
			<xmin>293</xmin>
			<xmax>313</xmax>
			<ymin>498</ymin>
			<ymax>517</ymax>
		</bndbox>
	</object>
	<object>
		<name>pustules</name>
		<pose>Unspecified</pose>
		<truncated>0</truncated>
		<difficult>0</difficult>
		<occluded>0</occluded>
		<bndbox>
			<xmin>228</xmin>
			<xmax>274</xmax>
			<ymin>524</ymin>
			<ymax>565</ymax>
		</bndbox>
	</object>
	<object>
		<name>pustules</name>
		<pose>Unspecified</pose>
		<truncated>0</truncated>
		<difficult>0</difficult>
		<occluded>0</occluded>
		<bndbox>
			<xmin>228</xmin>
			<xmax>267</xmax>
			<ymin>447</ymin>
			<ymax>485</ymax>
		</bndbox>
	</object>
	<object>
		<name>pustules</name>
		<pose>Unspecified</pose>
		<truncated>0</truncated>
		<difficult>0</difficult>
		<occluded>0</occluded>
		<bndbox>
			<xmin>229</xmin>
			<xmax>255</xmax>
			<ymin>64</ymin>
			<ymax>87</ymax>
		</bndbox>
	</object>
	<object>
		<name>pustules</name>
		<pose>Unspecified</pose>
		<truncated>0</truncated>
		<difficult>0</difficult>
		<occluded>0</occluded>
		<bndbox>
			<xmin>138</xmin>
			<xmax>169</xmax>
			<ymin>560</ymin>
			<ymax>591</ymax>
		</bndbox>
	</object>
	<object>
		<name>pustules</name>
		<pose>Unspecified</pose>
		<truncated>0</truncated>
		<difficult>0</difficult>
		<occluded>0</occluded>
		<bndbox>
			<xmin>153</xmin>
			<xmax>183</xmax>
			<ymin>531</ymin>
			<ymax>559</ymax>
		</bndbox>
	</object>
	<object>
		<name>pustules</name>
		<pose>Unspecified</pose>
		<truncated>0</truncated>
		<difficult>0</difficult>
		<occluded>0</occluded>
		<bndbox>
			<xmin>149</xmin>
			<xmax>177</xmax>
			<ymin>510</ymin>
			<ymax>529</ymax>
		</bndbox>
	</object>
	<object>
		<name>pustules</name>
		<pose>Unspecified</pose>
		<truncated>0</truncated>
		<difficult>0</difficult>
		<occluded>0</occluded>
		<bndbox>
			<xmin>117</xmin>
			<xmax>143</xmax>
			<ymin>508</ymin>
			<ymax>532</ymax>
		</bndbox>
	</object>
	<object>
		<name>pustules</name>
		<pose>Unspecified</pose>
		<truncated>0</truncated>
		<difficult>0</difficult>
		<occluded>0</occluded>
		<bndbox>
			<xmin>108</xmin>
			<xmax>142</xmax>
			<ymin>547</ymin>
			<ymax>577</ymax>
		</bndbox>
	</object>
	<metadata>
	</metadata>
</annotation>
