<annotation>
	<folder></folder>
	<filename>levle0_283_jpg.rf.58d9968cd73970fab6e9215976a581a5.jpg</filename>
	<path>levle0_283_jpg.rf.58d9968cd73970fab6e9215976a581a5.jpg</path>
	<source>
		<database>roboflow.com</database>
	</source>
	<size>
		<width>640</width>
		<height>640</height>
		<depth>3</depth>
	</size>
	<segmented>0</segmented>
	<object>
		<name>whitehead and blackhead</name>
		<pose>Unspecified</pose>
		<truncated>0</truncated>
		<difficult>0</difficult>
		<occluded>0</occluded>
		<bndbox>
			<xmin>208</xmin>
			<xmax>258</xmax>
			<ymin>548</ymin>
			<ymax>589</ymax>
		</bndbox>
	</object>
	<metadata>
	</metadata>
</annotation>
