<annotation>
	<folder></folder>
	<filename>levle1_392_jpg.rf.9b323c302d305490f20ef77a0d74f4f5.jpg</filename>
	<path>levle1_392_jpg.rf.9b323c302d305490f20ef77a0d74f4f5.jpg</path>
	<source>
		<database>roboflow.com</database>
	</source>
	<size>
		<width>640</width>
		<height>640</height>
		<depth>3</depth>
	</size>
	<segmented>0</segmented>
	<object>
		<name>pustules</name>
		<pose>Unspecified</pose>
		<truncated>0</truncated>
		<difficult>0</difficult>
		<occluded>0</occluded>
		<bndbox>
			<xmin>174</xmin>
			<xmax>210</xmax>
			<ymin>507</ymin>
			<ymax>546</ymax>
		</bndbox>
	</object>
	<object>
		<name>pustules</name>
		<pose>Unspecified</pose>
		<truncated>0</truncated>
		<difficult>0</difficult>
		<occluded>0</occluded>
		<bndbox>
			<xmin>200</xmin>
			<xmax>239</xmax>
			<ymin>483</ymin>
			<ymax>512</ymax>
		</bndbox>
	</object>
	<object>
		<name>pustules</name>
		<pose>Unspecified</pose>
		<truncated>0</truncated>
		<difficult>0</difficult>
		<occluded>0</occluded>
		<bndbox>
			<xmin>236</xmin>
			<xmax>278</xmax>
			<ymin>487</ymin>
			<ymax>520</ymax>
		</bndbox>
	</object>
	<object>
		<name>pustules</name>
		<pose>Unspecified</pose>
		<truncated>0</truncated>
		<difficult>0</difficult>
		<occluded>0</occluded>
		<bndbox>
			<xmin>155</xmin>
			<xmax>187</xmax>
			<ymin>567</ymin>
			<ymax>599</ymax>
		</bndbox>
	</object>
	<object>
		<name>pustules</name>
		<pose>Unspecified</pose>
		<truncated>0</truncated>
		<difficult>0</difficult>
		<occluded>0</occluded>
		<bndbox>
			<xmin>188</xmin>
			<xmax>200</xmax>
			<ymin>574</ymin>
			<ymax>593</ymax>
		</bndbox>
	</object>
	<object>
		<name>pustules</name>
		<pose>Unspecified</pose>
		<truncated>0</truncated>
		<difficult>0</difficult>
		<occluded>0</occluded>
		<bndbox>
			<xmin>250</xmin>
			<xmax>287</xmax>
			<ymin>540</ymin>
			<ymax>577</ymax>
		</bndbox>
	</object>
	<metadata>
	</metadata>
</annotation>
