<annotation>
	<folder></folder>
	<filename>levle1_353_jpg.rf.c218c91f74cc069a139cc2c5da12a735.jpg</filename>
	<path>levle1_353_jpg.rf.c218c91f74cc069a139cc2c5da12a735.jpg</path>
	<source>
		<database>roboflow.com</database>
	</source>
	<size>
		<width>640</width>
		<height>640</height>
		<depth>3</depth>
	</size>
	<segmented>0</segmented>
	<object>
		<name>pustules</name>
		<pose>Unspecified</pose>
		<truncated>0</truncated>
		<difficult>0</difficult>
		<occluded>0</occluded>
		<bndbox>
			<xmin>65</xmin>
			<xmax>103</xmax>
			<ymin>148</ymin>
			<ymax>184</ymax>
		</bndbox>
	</object>
	<object>
		<name>pustules</name>
		<pose>Unspecified</pose>
		<truncated>0</truncated>
		<difficult>0</difficult>
		<occluded>0</occluded>
		<bndbox>
			<xmin>54</xmin>
			<xmax>102</xmax>
			<ymin>187</ymin>
			<ymax>220</ymax>
		</bndbox>
	</object>
	<object>
		<name>pustules</name>
		<pose>Unspecified</pose>
		<truncated>0</truncated>
		<difficult>0</difficult>
		<occluded>0</occluded>
		<bndbox>
			<xmin>326</xmin>
			<xmax>365</xmax>
			<ymin>179</ymin>
			<ymax>195</ymax>
		</bndbox>
	</object>
	<object>
		<name>pustules</name>
		<pose>Unspecified</pose>
		<truncated>0</truncated>
		<difficult>0</difficult>
		<occluded>0</occluded>
		<bndbox>
			<xmin>361</xmin>
			<xmax>397</xmax>
			<ymin>120</ymin>
			<ymax>154</ymax>
		</bndbox>
	</object>
	<object>
		<name>pustules</name>
		<pose>Unspecified</pose>
		<truncated>0</truncated>
		<difficult>0</difficult>
		<occluded>0</occluded>
		<bndbox>
			<xmin>444</xmin>
			<xmax>479</xmax>
			<ymin>172</ymin>
			<ymax>215</ymax>
		</bndbox>
	</object>
	<object>
		<name>pustules</name>
		<pose>Unspecified</pose>
		<truncated>0</truncated>
		<difficult>0</difficult>
		<occluded>0</occluded>
		<bndbox>
			<xmin>132</xmin>
			<xmax>167</xmax>
			<ymin>418</ymin>
			<ymax>460</ymax>
		</bndbox>
	</object>
	<object>
		<name>pustules</name>
		<pose>Unspecified</pose>
		<truncated>0</truncated>
		<difficult>0</difficult>
		<occluded>0</occluded>
		<bndbox>
			<xmin>224</xmin>
			<xmax>251</xmax>
			<ymin>440</ymin>
			<ymax>472</ymax>
		</bndbox>
	</object>
	<object>
		<name>pustules</name>
		<pose>Unspecified</pose>
		<truncated>0</truncated>
		<difficult>0</difficult>
		<occluded>0</occluded>
		<bndbox>
			<xmin>247</xmin>
			<xmax>273</xmax>
			<ymin>442</ymin>
			<ymax>470</ymax>
		</bndbox>
	</object>
	<object>
		<name>pustules</name>
		<pose>Unspecified</pose>
		<truncated>0</truncated>
		<difficult>0</difficult>
		<occluded>0</occluded>
		<bndbox>
			<xmin>265</xmin>
			<xmax>309</xmax>
			<ymin>475</ymin>
			<ymax>512</ymax>
		</bndbox>
	</object>
	<object>
		<name>pustules</name>
		<pose>Unspecified</pose>
		<truncated>0</truncated>
		<difficult>0</difficult>
		<occluded>0</occluded>
		<bndbox>
			<xmin>281</xmin>
			<xmax>314</xmax>
			<ymin>609</ymin>
			<ymax>635</ymax>
		</bndbox>
	</object>
	<object>
		<name>pustules</name>
		<pose>Unspecified</pose>
		<truncated>0</truncated>
		<difficult>0</difficult>
		<occluded>0</occluded>
		<bndbox>
			<xmin>272</xmin>
			<xmax>301</xmax>
			<ymin>425</ymin>
			<ymax>455</ymax>
		</bndbox>
	</object>
	<metadata>
	</metadata>
</annotation>
