<annotation>
	<folder></folder>
	<filename>levle0_279_jpg.rf.e833155ac886da166a1491cc731d9df1.jpg</filename>
	<path>levle0_279_jpg.rf.e833155ac886da166a1491cc731d9df1.jpg</path>
	<source>
		<database>roboflow.com</database>
	</source>
	<size>
		<width>640</width>
		<height>640</height>
		<depth>3</depth>
	</size>
	<segmented>0</segmented>
	<object>
		<name>whitehead and blackhead</name>
		<pose>Unspecified</pose>
		<truncated>0</truncated>
		<difficult>0</difficult>
		<occluded>0</occluded>
		<bndbox>
			<xmin>493</xmin>
			<xmax>533</xmax>
			<ymin>279</ymin>
			<ymax>304</ymax>
		</bndbox>
	</object>
	<object>
		<name>whitehead and blackhead</name>
		<pose>Unspecified</pose>
		<truncated>0</truncated>
		<difficult>0</difficult>
		<occluded>0</occluded>
		<bndbox>
			<xmin>375</xmin>
			<xmax>420</xmax>
			<ymin>442</ymin>
			<ymax>479</ymax>
		</bndbox>
	</object>
	<object>
		<name>whitehead and blackhead</name>
		<pose>Unspecified</pose>
		<truncated>0</truncated>
		<difficult>0</difficult>
		<occluded>0</occluded>
		<bndbox>
			<xmin>270</xmin>
			<xmax>306</xmax>
			<ymin>573</ymin>
			<ymax>603</ymax>
		</bndbox>
	</object>
	<metadata>
	</metadata>
</annotation>
