<annotation>
	<folder></folder>
	<filename>levle1_128_jpg.rf.995d5815aa4cf889faa5341bb1119f54.jpg</filename>
	<path>levle1_128_jpg.rf.995d5815aa4cf889faa5341bb1119f54.jpg</path>
	<source>
		<database>roboflow.com</database>
	</source>
	<size>
		<width>640</width>
		<height>640</height>
		<depth>3</depth>
	</size>
	<segmented>0</segmented>
	<object>
		<name>pustules</name>
		<pose>Unspecified</pose>
		<truncated>0</truncated>
		<difficult>0</difficult>
		<occluded>0</occluded>
		<bndbox>
			<xmin>166</xmin>
			<xmax>195</xmax>
			<ymin>436</ymin>
			<ymax>463</ymax>
		</bndbox>
	</object>
	<object>
		<name>pustules</name>
		<pose>Unspecified</pose>
		<truncated>0</truncated>
		<difficult>0</difficult>
		<occluded>0</occluded>
		<bndbox>
			<xmin>157</xmin>
			<xmax>185</xmax>
			<ymin>421</ymin>
			<ymax>443</ymax>
		</bndbox>
	</object>
	<object>
		<name>pustules</name>
		<pose>Unspecified</pose>
		<truncated>0</truncated>
		<difficult>0</difficult>
		<occluded>0</occluded>
		<bndbox>
			<xmin>206</xmin>
			<xmax>238</xmax>
			<ymin>413</ymin>
			<ymax>446</ymax>
		</bndbox>
	</object>
	<object>
		<name>pustules</name>
		<pose>Unspecified</pose>
		<truncated>0</truncated>
		<difficult>0</difficult>
		<occluded>0</occluded>
		<bndbox>
			<xmin>181</xmin>
			<xmax>208</xmax>
			<ymin>488</ymin>
			<ymax>513</ymax>
		</bndbox>
	</object>
	<object>
		<name>pustules</name>
		<pose>Unspecified</pose>
		<truncated>0</truncated>
		<difficult>0</difficult>
		<occluded>0</occluded>
		<bndbox>
			<xmin>226</xmin>
			<xmax>263</xmax>
			<ymin>526</ymin>
			<ymax>561</ymax>
		</bndbox>
	</object>
	<object>
		<name>pustules</name>
		<pose>Unspecified</pose>
		<truncated>0</truncated>
		<difficult>0</difficult>
		<occluded>0</occluded>
		<bndbox>
			<xmin>237</xmin>
			<xmax>266</xmax>
			<ymin>498</ymin>
			<ymax>526</ymax>
		</bndbox>
	</object>
	<object>
		<name>pustules</name>
		<pose>Unspecified</pose>
		<truncated>0</truncated>
		<difficult>0</difficult>
		<occluded>0</occluded>
		<bndbox>
			<xmin>161</xmin>
			<xmax>211</xmax>
			<ymin>520</ymin>
			<ymax>548</ymax>
		</bndbox>
	</object>
	<metadata>
	</metadata>
</annotation>
